pytoshop/__init__.py
pytoshop/blending_range.py
pytoshop/codecs.py
pytoshop/color_mode.py
pytoshop/core.py
pytoshop/docs.py
pytoshop/enums.py
pytoshop/image_data.py
pytoshop/image_resources.py
pytoshop/layers.py
pytoshop/packbits.c
pytoshop/packbits.cpython-35m-darwin.so
pytoshop/path.py
pytoshop/tagged_block.py
pytoshop/util.py
pytoshop/user/__init__.py
pytoshop/user/nested_layers.py
pytoshop-0.3.0.dist-info/DESCRIPTION.rst
pytoshop-0.3.0.dist-info/METADATA
pytoshop-0.3.0.dist-info/RECORD
pytoshop-0.3.0.dist-info/WHEEL
pytoshop-0.3.0.dist-info/metadata.json
pytoshop-0.3.0.dist-info/top_level.txt
