Metadata-Version: 2.0
Name: pytoshop
Version: 0.3.0
Summary: A Python-based library to write Photoshop PSD files
Home-page: https://github.com/mdboom/pytoshop
Author: Michael Droettboom
Author-email: mdboom@gmail.com
License: BSD license
Keywords: pytoshop
Platform: UNKNOWN
Classifier: Development Status :: 2 - Pre-Alpha
Classifier: Intended Audience :: Developers
Classifier: License :: OSI Approved :: BSD License
Classifier: Natural Language :: English
Classifier: Programming Language :: Python :: 2.7
Classifier: Programming Language :: Python :: 3.4
Classifier: Programming Language :: Python :: 3.5
Classifier: Programming Language :: Python :: 3.6
Requires-Dist: cython
Requires-Dist: numpy
Requires-Dist: traitlets
